smi_python_commons/__init__.py
smi_python_commons/project.py
smi_python_commons/scm_version.py
smi_python_commons/arguments/__init__.py
smi_python_commons/arguments/argument.py
smi_python_commons/arguments/config.py
smi_python_commons/arguments/constants.py
smi_python_commons/arguments/parser.py
smi_python_commons/config/__init__.py
smi_python_commons/config/application.py
smi_python_commons/config/constants.py
smi_python_commons/environment/__init__.py
smi_python_commons/environment/variables.py
smi_python_commons/file/__init__.py
smi_python_commons/file/operations.py
smi_python_commons/json/__init__.py
smi_python_commons/json/parser.py
smi_python_commons/string/__init__.py
smi_python_commons/string/operations.py
smi_python_commons/yaml/__init__.py
smi_python_commons/yaml/parser.py
test/__init__.py
test/info/__init__.py
test/info/setmy/__init__.py
test/info/setmy/arguments/__init__.py
test/info/setmy/arguments/test_parser.py
test/info/setmy/config/__init__.py
test/info/setmy/config/it_application.py
test/info/setmy/string/__init__.py
test/info/setmy/string/test_operations.py
smi_python_commons-0.3.3.dist-info/LICENSE
smi_python_commons-0.3.3.dist-info/METADATA
smi_python_commons-0.3.3.dist-info/WHEEL
smi_python_commons-0.3.3.dist-info/top_level.txt
smi_python_commons-0.3.3.dist-info/RECORD
