Metadata-Version: 2.1
Name: smi-python-commons
Version: 0.3.3
Summary: setmy.info python commons library.
Home-page: https://github.com/setmy-info/python-commons
Author: Imre Tabur
Author-email: info@setmy.info
License: MIT
License-File: LICENSE
Requires-Dist: pyyaml ==6.0.1
